pykooh/__init__.py
pykooh/smooth_numba.py
pykooh-0.5.0.dist-info/METADATA
pykooh-0.5.0.dist-info/WHEEL
pykooh-0.5.0.dist-info/licenses/LICENSE
pykooh-0.5.0.dist-info/RECORD
