Metadata-Version: 2.4
Name: pyKOOH
Version: 0.5.0
Summary: Efficient implementatins of the Konno Ohmachi filter in Python.
Project-URL: Homepage, https://github.com/arkottke/pykooh
Author-email: Albert Kottke <albert.kottke@gmail.com>
License: MIT
License-File: LICENSE
Requires-Python: >=3.10
Requires-Dist: numba
Requires-Dist: numpy
Requires-Dist: setuptools
